dlwinesd/__init__.py
dlwinesd-0.1.dist-info/LICENSE.txt
dlwinesd-0.1.dist-info/METADATA
dlwinesd-0.1.dist-info/WHEEL
dlwinesd-0.1.dist-info/entry_points.txt
dlwinesd-0.1.dist-info/top_level.txt
dlwinesd-0.1.dist-info/RECORD
